{
  "6395738130": {
    "username": "axeliandrea",
    "points": 28371,
    "level": 4,
    "last_milestone": 990100
  },
  "6467053561": {
    "username": "axeliandreaaa",
    "points": 99039,
    "level": 7,
    "last_milestone": 990
  },
  "6621460606": {
    "username": "axeliandrea_3",
    "points": 414,
    "level": 0,
    "last_milestone": 5000
  },
  "1780930479": {
    "username": "riaaaw1",
    "points": 13780,
    "level": 1,
    "last_milestone": 137
  },
  "6580176261": {
    "username": "iniannnnY",
    "points": 7492,
    "level": 0,
    "last_milestone": 74
  },
  "7560156334": {
    "username": "chovlaaattee",
    "points": 3846,
    "level": 0,
    "last_milestone": 38
  },
  "1330957309": {
    "username": "csviaww5",
    "points": 21425,
    "level": 3,
    "last_milestone": 214
  },
  "1183769897": {
    "username": "Meiyliaaa",
    "points": 7408,
    "level": 0,
    "last_milestone": 74
  },
  "5865394235": {
    "username": "strawcihuy",
    "points": 6431,
    "level": 0,
    "last_milestone": 64
  },
  "6742407313": {
    "username": "Farclad22",
    "points": 2928,
    "level": 0,
    "last_milestone": 29
  },
  "6190676802": {
    "username": "Kembalidengansaya",
    "points": 431,
    "level": 0,
    "last_milestone": 4
  },
  "6389981192": {
    "username": "Iam_Nisssss",
    "points": 6421,
    "level": 0,
    "last_milestone": 64
  },
  "689421283": {
    "username": "RisnaC",
    "points": 230,
    "level": 0,
    "last_milestone": 2
  },
  "2066716157": {
    "username": "betmenXnyirorokidul",
    "points": 38,
    "level": 0,
    "last_milestone": 40
  },
  "5267223403": {
    "username": "haiparahaters",
    "points": 519,
    "level": 0,
    "last_milestone": 5
  },
  "1327484747": {
    "username": "KKYERIMIE99",
    "points": 5339,
    "level": 0,
    "last_milestone": 53
  },
  "7924900171": {
    "username": "kelinciliar",
    "points": 4821,
    "level": 0,
    "last_milestone": 48
  },
  "7733315523": {
    "username": "No7meeee",
    "points": 164,
    "level": 0,
    "last_milestone": 4
  },
  "7618644454": {
    "username": "nanaaa12234",
    "points": 22,
    "level": 0,
    "last_milestone": 0
  },
  "1407066606": {
    "username": "Tweetyballs",
    "points": 8012,
    "level": 0,
    "last_milestone": 80
  },
  "1462625484": {
    "username": "laeeeeeeea",
    "points": 1943,
    "level": 0,
    "last_milestone": 19
  },
  "5166986911": {
    "username": "Glukoneogenesis4",
    "points": 678,
    "level": 0,
    "last_milestone": 6
  },
  "7435721456": {
    "username": "tumbleweedx",
    "points": 1306,
    "level": 0,
    "last_milestone": 13
  },
  "6571483292": {
    "username": "brokoligur",
    "points": 31098,
    "level": 4,
    "last_milestone": 310
  },
  "8103582471": {
    "username": "JustAnOrdinaryGirlll",
    "points": 9867,
    "level": 0,
    "last_milestone": 98
  },
  "7685814466": {
    "username": "Manisuyy",
    "points": 6316,
    "level": 0,
    "last_milestone": 63
  },
  "904782898": {
    "username": "nnikikulo",
    "points": 243,
    "level": 0,
    "last_milestone": 11
  },
  "8131749096": {
    "username": "Caimisii",
    "points": 4041,
    "level": 0,
    "last_milestone": 40
  },
  "6644199317": {
    "username": "ssa2480",
    "points": 6753,
    "level": 0,
    "last_milestone": 67
  },
  "7507554734": {
    "username": "iearce",
    "points": 1043,
    "level": 0,
    "last_milestone": 10
  },
  "6311531502": {
    "username": "xerennaaas",
    "points": 314,
    "level": 0,
    "last_milestone": 3
  },
  "5409201162": {
    "username": "zaaraaulia",
    "points": 6399,
    "level": 0,
    "last_milestone": 63
  },
  "8050528403": {
    "username": "strraawb3rry",
    "points": 3855,
    "level": 0,
    "last_milestone": 38
  },
  "1910337710": {
    "username": "ansyarara",
    "points": 1550,
    "level": 0,
    "last_milestone": 15
  },
  "6789290524": {
    "username": "Dityaa3393",
    "points": 27199,
    "level": 3,
    "last_milestone": 286
  },
  "6385363971": {
    "username": "mvgstyel",
    "points": 2822,
    "level": 0,
    "last_milestone": 28
  },
  "5926231066": {
    "username": "Sszafamily",
    "points": 4632,
    "level": 0,
    "last_milestone": 46
  },
  "6307466693": {
    "username": "Strzlaw",
    "points": 275,
    "level": 0,
    "last_milestone": 2
  },
  "8004713258": {
    "username": "mushrawr",
    "points": 139,
    "level": 0,
    "last_milestone": 1
  },
  "7341241548": {
    "username": "Chantikacc",
    "points": 559,
    "level": 0,
    "last_milestone": 47
  },
  "6936490199": {
    "username": "Xyxy_laaaaaaaaaaa",
    "points": 2176,
    "level": 0,
    "last_milestone": 21
  },
  "8112963625": {
    "username": "misscashflow",
    "points": 998,
    "level": 0,
    "last_milestone": 10
  },
  "7846680289": {
    "username": "wfunyyy",
    "points": 212,
    "level": 0,
    "last_milestone": 2
  },
  "7444201720": {
    "username": "yuniocta",
    "points": 176,
    "level": 0,
    "last_milestone": 1
  },
  "8073479792": {
    "username": "Sayangin_orang_tua_mu_selagi_ada",
    "points": 1889,
    "level": 0,
    "last_milestone": 18
  },
  "5329469686": {
    "username": "belbel666",
    "points": 2417,
    "level": 0,
    "last_milestone": 24
  },
  "6353936030": {
    "username": "ccccccipp",
    "points": 138,
    "level": 0,
    "last_milestone": 1
  },
  "7194411444": {
    "username": "genntaaaaa",
    "points": 609,
    "level": 0,
    "last_milestone": 6
  },
  "1575921342": {
    "username": "Setianingrum19",
    "points": 25,
    "level": 0,
    "last_milestone": 0
  },
  "5258093045": {
    "username": "galihnabilasalma",
    "points": 2002,
    "level": 0,
    "last_milestone": 20
  },
  "6769845093": {
    "username": "love3542",
    "points": 2411,
    "level": 0,
    "last_milestone": 24
  },
  "7300803565": {
    "username": "cicacaica",
    "points": 1511,
    "level": 0,
    "last_milestone": 15
  },
  "7324278553": {
    "username": "oomuaknya",
    "points": 5699,
    "level": 0,
    "last_milestone": 56
  },
  "5730210357": {
    "username": "XDisableVY",
    "points": 109,
    "level": 0,
    "last_milestone": 1
  },
  "7958947136": {
    "username": "hon33yhere",
    "points": 2157,
    "level": 0,
    "last_milestone": 21
  },
  "6509224848": {
    "username": "KertasOrigamie",
    "points": 65,
    "level": 0,
    "last_milestone": 0
  },
  "8232689660": {
    "username": "aproIoG",
    "points": 15,
    "level": 0,
    "last_milestone": 0
  },
  "6215874995": {
    "username": "Eleanor_lex",
    "points": 468,
    "level": 0,
    "last_milestone": 4
  },
  "5384772170": {
    "username": "mathsomuch",
    "points": 321,
    "level": 0,
    "last_milestone": 3
  },
  "8056359575": {
    "username": "ususmeledak",
    "points": 525,
    "level": 0,
    "last_milestone": 5
  },
  "5324087886": {
    "username": "arianagea",
    "points": 2106,
    "level": 0,
    "last_milestone": 21
  },
  "5831741318": {
    "username": "putridamayana",
    "points": 1601,
    "level": 0,
    "last_milestone": 16
  },
  "1822994962": {
    "username": "ArkhaNandez",
    "points": 295,
    "level": 0,
    "last_milestone": 2
  },
  "8013248287": {
    "username": "Vallyall",
    "points": 182,
    "level": 0,
    "last_milestone": 1
  },
  "6600824828": {
    "username": "MASSSSSSSS_REZAAAAAAAA_yooooooo",
    "points": 292,
    "level": 0,
    "last_milestone": 2
  },
  "6460908646": {
    "username": "kmsiapaia",
    "points": 2514,
    "level": 0,
    "last_milestone": 25
  },
  "6534127517": {
    "username": "Pikachu17903",
    "points": 409,
    "level": 0,
    "last_milestone": 4
  },
  "8015046171": {
    "username": "BinBinsoooo",
    "points": 177,
    "level": 0,
    "last_milestone": 1
  },
  "8132460972": {
    "username": "agnsmrgrth",
    "points": 876,
    "level": 0,
    "last_milestone": 8
  },
  "7531972318": {
    "username": "Fajjarzx_25",
    "points": 349,
    "level": 0,
    "last_milestone": 3
  },
  "5109461945": {
    "username": "theEnd134567892",
    "points": 21030,
    "level": 3,
    "last_milestone": 210
  },
  "1630624318": {
    "username": "steppie96",
    "points": 3362,
    "level": 0,
    "last_milestone": 33
  },
  "1764329591": {
    "username": "behappierss",
    "points": 37,
    "level": 0,
    "last_milestone": 0
  },
  "6478047444": {
    "username": "lllaaou",
    "points": 49,
    "level": 0,
    "last_milestone": 0
  },
  "7672230822": {
    "username": "kucinggaronggga",
    "points": 596,
    "level": 0,
    "last_milestone": 5
  },
  "6745365116": {
    "username": "Iriiidekk",
    "points": 1074,
    "level": 0,
    "last_milestone": 10
  },
  "6557336599": {
    "username": "aukagelap",
    "points": 384,
    "level": 0,
    "last_milestone": 3
  },
  "5302307390": {
    "username": "weareber",
    "points": 44,
    "level": 0,
    "last_milestone": 0
  },
  "1326876567": {
    "username": "Akaushjs",
    "points": 326,
    "level": 0,
    "last_milestone": 3
  },
  "6025041989": {
    "username": "Anakbaekhatie",
    "points": 546,
    "level": 0,
    "last_milestone": 5
  },
  "6650112459": {
    "username": "acikiwirrrblele",
    "points": 26,
    "level": 0,
    "last_milestone": 0
  },
  "7239573288": {
    "username": "NNcnald",
    "points": 339,
    "level": 0,
    "last_milestone": 3
  },
  "5102350010": {
    "username": "emcorz",
    "points": 111,
    "level": 0,
    "last_milestone": 1
  },
  "7651622862": {
    "username": "Aluna_LITTLEGIRLL",
    "points": 95,
    "level": 0,
    "last_milestone": 0
  },
  "2097520464": {
    "username": "sayangggggggggghh",
    "points": 281,
    "level": 0,
    "last_milestone": 2
  },
  "8308465748": {
    "username": "namakukeen",
    "points": 91,
    "level": 0,
    "last_milestone": 0
  },
  "6184265498": {
    "username": "weareoneaa",
    "points": 505,
    "level": 0,
    "last_milestone": 5
  },
  "8478395897": {
    "username": "zaydhe",
    "points": 21,
    "level": 0,
    "last_milestone": 0
  },
  "6670429962": {
    "username": "Hihialokk",
    "points": 4,
    "level": 0,
    "last_milestone": 0
  },
  "739519290": {
    "username": "niche3535",
    "points": 328,
    "level": 0,
    "last_milestone": 3
  },
  "5971666527": {
    "username": "risyyxll",
    "points": 183,
    "level": 0,
    "last_milestone": 1
  },
  "6959760405": {
    "username": "idknowwangy",
    "points": 1752,
    "level": 0,
    "last_milestone": 17
  },
  "8229868104": {
    "username": "lsya4u",
    "points": 5,
    "level": 0,
    "last_milestone": 0
  },
  "8110667539": {
    "username": "sakhronik",
    "points": 1680,
    "level": 0,
    "last_milestone": 16
  },
  "5875745650": {
    "username": "gatauakucapek",
    "points": 369,
    "level": 0,
    "last_milestone": 3
  },
  "5778594119": {
    "username": "akurindurumah",
    "points": 51,
    "level": 0,
    "last_milestone": 0
  },
  "6819025347": {
    "username": "soeunxe",
    "points": 61,
    "level": 0,
    "last_milestone": 0
  },
  "7717036620": {
    "username": "aiiishiball",
    "points": 182,
    "level": 0,
    "last_milestone": 1
  },
  "8481825823": {
    "username": "komanganakketigaaaa",
    "points": 170,
    "level": 0,
    "last_milestone": 1
  },
  "6658724626": {
    "username": "smntkq",
    "points": 216,
    "level": 0,
    "last_milestone": 2
  },
  "7851878412": {
    "username": "SrigalaTerakhirrr",
    "points": 875,
    "level": 0,
    "last_milestone": 8
  },
  "7405525319": {
    "username": "alipp1uu",
    "points": 3165,
    "level": 0,
    "last_milestone": 31
  },
  "1718673265": {
    "username": "Siinnn_23",
    "points": 491,
    "level": 0,
    "last_milestone": 4
  },
  "628981410": {
    "username": "NetworkSolana",
    "points": 946,
    "level": 0,
    "last_milestone": 9
  },
  "5999051777": {
    "username": "giniyaexcitedndili",
    "points": 106,
    "level": 0,
    "last_milestone": 1
  },
  "1185503937": {
    "username": "callmedifff",
    "points": 3,
    "level": 0,
    "last_milestone": 0
  },
  "6213252958": {
    "username": "Hupplahup",
    "points": 12,
    "level": 0,
    "last_milestone": 0
  },
  "6953227169": {
    "username": "lyricsxuxu",
    "points": 46,
    "level": 0,
    "last_milestone": 0
  },
  "6919471772": {
    "username": "ffaa_37",
    "points": 659,
    "level": 0,
    "last_milestone": 6
  },
  "7829798830": {
    "username": "peacyy1",
    "points": 290,
    "level": 0,
    "last_milestone": 3
  },
  "7464644499": {
    "username": "Rainwannabeyours",
    "points": 38,
    "level": 0,
    "last_milestone": 0
  },
  "6778822705": {
    "username": "nnorenn",
    "points": 15,
    "level": 0,
    "last_milestone": 0
  },
  "7521551880": {
    "username": "ndaaaaaaaaai",
    "points": 0,
    "level": 0,
    "last_milestone": 0
  },
  "7961614045": {
    "username": "riolfrndt18",
    "points": 449,
    "level": 0,
    "last_milestone": 4
  },
  "7659089582": {
    "username": "varinn95",
    "points": 1,
    "level": 0,
    "last_milestone": 0
  },
  "7427494409": {
    "username": "ummiazella",
    "points": 701,
    "level": 0,
    "last_milestone": 7
  },
  "933482815": {
    "username": "user_idNav",
    "points": 4747,
    "level": 0,
    "last_milestone": 47
  },
  "1725768997": {
    "username": "Ai_Ni_Kipuka",
    "points": 7,
    "level": 0,
    "last_milestone": 0
  },
  "6252242957": {
    "username": "koyuki_ii",
    "points": 7,
    "level": 0,
    "last_milestone": 0
  },
  "8181978968": {
    "username": "thlnbila",
    "points": 10,
    "level": 0,
    "last_milestone": 0
  },
  "1893770139": {
    "username": "bealllalalaa",
    "points": 42,
    "level": 0,
    "last_milestone": 0
  },
  "1208155104": {
    "username": "jjjfffa",
    "points": 97,
    "level": 0,
    "last_milestone": 0
  },
  "7838404742": {
    "username": "zyenzaa",
    "points": 53,
    "level": 0,
    "last_milestone": 0
  },
  "7716881180": {
    "username": "xxxknjtt",
    "points": 11,
    "level": 0,
    "last_milestone": 1
  },
  "6629087459": {
    "username": "deennde",
    "points": 150,
    "level": 0,
    "last_milestone": 1
  },
  "6212568982": {
    "username": "astertila",
    "points": 12,
    "level": 0,
    "last_milestone": 0
  },
  "1358719073": {
    "username": "babyboybintang",
    "points": 1,
    "level": 0,
    "last_milestone": 0
  },
  "7393317126": {
    "username": "formeiloveit",
    "points": 181,
    "level": 0,
    "last_milestone": 1
  },
  "8042951394": {
    "username": "kejudimsummentai",
    "points": 130,
    "level": 0,
    "last_milestone": 1
  },
  "6814360718": {
    "username": "vxennee",
    "points": 130,
    "level": 0,
    "last_milestone": 1
  },
  "5283119407": {
    "username": "c4ncatie",
    "points": 52,
    "level": 0,
    "last_milestone": 0
  },
  "5187061369": {
    "username": "geeeckp",
    "points": 26,
    "level": 0,
    "last_milestone": 0
  },
  "5734099837": {
    "username": "Mbekkku",
    "points": 6,
    "level": 0,
    "last_milestone": 0
  },
  "7497739919": {
    "username": "urfvzn",
    "points": 121,
    "level": 0,
    "last_milestone": 1
  },
  "7861563520": {
    "username": "pipenlut",
    "points": 6,
    "level": 0,
    "last_milestone": 0
  },
  "5709659461": {
    "username": "shals4",
    "points": 13,
    "level": 0,
    "last_milestone": 0
  },
  "5110055485": {
    "username": "titiklusyu",
    "points": 321,
    "level": 0,
    "last_milestone": 3
  },
  "7573110203": {
    "username": "oxeata",
    "points": 2,
    "level": 0,
    "last_milestone": 0
  },
  "6170955086": {
    "username": "crocodile_elite",
    "points": 16,
    "level": 0,
    "last_milestone": 0
  },
  "6731593749": {
    "username": "bbyanmnp",
    "points": 515,
    "level": 0,
    "last_milestone": 5
  },
  "7902573212": {
    "username": "faz200000e",
    "points": 211,
    "level": 0,
    "last_milestone": 2
  },
  "7736940934": {
    "username": "callenayola",
    "points": 2,
    "level": 0,
    "last_milestone": 0
  },
  "7927290202": {
    "username": "ihaeinezzzzzzzzzz",
    "points": 25,
    "level": 0,
    "last_milestone": 0
  },
  "7922175616": {
    "username": "satinee",
    "points": 53,
    "level": 0,
    "last_milestone": 0
  },
  "8221918791": {
    "username": "tatakdungtaq",
    "points": 44,
    "level": 0,
    "last_milestone": 0
  },
  "5404374106": {
    "username": "bestfuckinGirll",
    "points": 642,
    "level": 0,
    "last_milestone": 6
  },
  "1609812473": {
    "username": "apksnwk2",
    "points": 17,
    "level": 0,
    "last_milestone": 0
  },
  "8425494524": {
    "username": "Mascuzline",
    "points": 54,
    "level": 0,
    "last_milestone": 0
  },
  "7670198190": {
    "username": "olayslay",
    "points": 3,
    "level": 0,
    "last_milestone": 0
  },
  "6467417597": {
    "username": "\ufe0e\ufe0enona\ud80c\udcd7",
    "points": 9,
    "level": 0,
    "last_milestone": 0
  }
}